setup.py
Units/SI.py
Units/__init__.py
Units/area.py
Units/density.py
Units/energy.py
Units/force.py
Units/length.py
Units/mass.py
Units/power.py
Units/pressure.py
Units/specificEnergy.py
Units/specificEntropy.py
Units/speed.py
Units/temperature.py
Units/time.py
Units/unit.py
Units/volume.py
mixmaster.egg-info/PKG-INFO
mixmaster.egg-info/SOURCES.txt
mixmaster.egg-info/dependency_links.txt
mixmaster.egg-info/requires.txt
mixmaster.egg-info/top_level.txt