Metadata-Version: 1.0
Name: mixmaster
Version: 1.0
Summary: Mixmaster is a Cantera based GUI that allows you to import reaction mechanisms and to view or set the state of mixtures.It can carry out the thermodynamic processes adn compute the chemical equilibrium. It gives the data related to reaction and chemical species. It postprocess the simulation data ans shows the reaction paths.   
Home-page: https://github.com/Cantera/mixmaster
Author: Ray Speth, Bryan W. Weber
Author-email: yarmond@gmail.com, bryan.w.weber@gmail.com
License: MIT
Platform: UNKNOWN
